swedishfurniture/__init__.py
swedishfurniture/data.py
swedishfurniture/export.py
swedishfurniture/generator.py
swedishfurniture/morphemes.py
swedishfurniture/patterns.py
swedishfurniture/utils.py
swedishfurniture-1.0.2.dist-info/licenses/LICENSE
swedishfurniture-1.0.2.dist-info/METADATA
swedishfurniture-1.0.2.dist-info/WHEEL
swedishfurniture-1.0.2.dist-info/top_level.txt
swedishfurniture-1.0.2.dist-info/RECORD
