Metadata-Version: 2.4
Name: SwedishFurniture
Version: 1.0.2
Summary: Furniture name generator like a popular Swedish company does it.
Author: Mikhail
License: MIT
Requires-Python: >=3.7
License-File: LICENSE
Dynamic: license-file
